aiida_gulp/__init__.py
aiida_gulp/unit_styles.py
aiida_gulp/calculations/__init__.py
aiida_gulp/calculations/gulp_abstract.py
aiida_gulp/calculations/gulp_fitting.py
aiida_gulp/calculations/gulp_optimize.py
aiida_gulp/calculations/gulp_single.py
aiida_gulp/cmndline/__init__.py
aiida_gulp/cmndline/potentials.py
aiida_gulp/common/__init__.py
aiida_gulp/common/atoms.py
aiida_gulp/common/dict_funcs.py
aiida_gulp/common/kpoints.py
aiida_gulp/common/mapping.py
aiida_gulp/common/parsing.py
aiida_gulp/data/__init__.py
aiida_gulp/data/potential.py
aiida_gulp/data/symmetry.py
aiida_gulp/parsers/__init__.py
aiida_gulp/parsers/parse_fitting.py
aiida_gulp/parsers/parse_opt.py
aiida_gulp/parsers/parse_single.py
aiida_gulp/parsers/raw/__init__.py
aiida_gulp/parsers/raw/parse_output_common.py
aiida_gulp/parsers/raw/parse_output_fit.py
aiida_gulp/parsers/raw/parse_output_std.py
aiida_gulp/parsers/raw/write_geometry.py
aiida_gulp/parsers/raw/write_input.py
aiida_gulp/parsers/raw/write_input_fitting.py
aiida_gulp/potentials/__init__.py
aiida_gulp/potentials/base.py
aiida_gulp/potentials/common.py
aiida_gulp/potentials/lj.py
aiida_gulp/potentials/raw_reaxff.py
aiida_gulp/potentials/reaxff.py
aiida_gulp/symmetry/__init__.py
aiida_gulp/symmetry/symmetry.py
aiida_gulp/tests/__init__.py
aiida_gulp/tests/mock_gulp.py
aiida_gulp/tests/resources.py
aiida_gulp/tests/utils.py
aiida_gulp/tests/raw_files/__init__.py
aiida_gulp/tests/raw_files/cif/__init__.py
aiida_gulp/tests/raw_files/cif/pyrite.cif
aiida_gulp/tests/raw_files/gulp/__init__.py
aiida_gulp/tests/raw_files/gulp/failed/__init__.py
aiida_gulp/tests/raw_files/gulp/failed/empty_error.gout
aiida_gulp/tests/raw_files/gulp/failed/opt_step_limit.gout
aiida_gulp/tests/raw_files/gulp/fit_lj_fes/__init__.py
aiida_gulp/tests/raw_files/gulp/fit_lj_fes/fitting.grs
aiida_gulp/tests/raw_files/gulp/fit_lj_fes/main.gin
aiida_gulp/tests/raw_files/gulp/fit_lj_fes/main.gout
aiida_gulp/tests/raw_files/gulp/fit_lj_fes/main_stderr.txt
aiida_gulp-0.10.0b5.dist-info/LICENSE
aiida_gulp-0.10.0b5.dist-info/METADATA
aiida_gulp-0.10.0b5.dist-info/WHEEL
aiida_gulp-0.10.0b5.dist-info/entry_points.txt
aiida_gulp-0.10.0b5.dist-info/top_level.txt
aiida_gulp-0.10.0b5.dist-info/RECORD
