Metadata-Version: 2.1
Name: aiida-gulp
Version: 0.10.0b5
Summary: AiiDA plugin for running the GULP MD code
Home-page: https://github.com/chrisjsewell/aiida-gulp
Author: Chris Sewell
Author-email: chrisj_sewell@hotmail.com
License: MIT
Platform: UNKNOWN
Classifier: Programming Language :: Python
Classifier: Programming Language :: Python :: 2.7
Classifier: Programming Language :: Python :: 3.6
Classifier: Topic :: Scientific/Engineering :: Chemistry
Classifier: Topic :: Scientific/Engineering :: Physics
Classifier: Framework :: AiiDA
Requires-Dist: aiida-core (==1.0.0b5)
Requires-Dist: six (>=1.12.0)
Requires-Dist: ruamel.yaml
Requires-Dist: jsonextended (>=0.7.10)
Requires-Dist: jsonschema
Requires-Dist: spglib (<2.0.0,>=1.10.0)
Requires-Dist: importlib-resources
Requires-Dist: ase (<3.18.0,>=3.12.0) ; python_version < "3"
Requires-Dist: PyCifRW (==4.2.1) ; python_version < "3"
Requires-Dist: pathlib2 ; python_version < "3.4"
Requires-Dist: ase (<4.0.0,>=3.12.0) ; python_version >= "3"
Requires-Dist: PyCifRW (==4.4) ; python_version >= "3"
Provides-Extra: code_style
Requires-Dist: black (==19.3b0) ; extra == 'code_style'
Requires-Dist: flake8 (<3.8.0,>=3.7.0) ; extra == 'code_style'
Requires-Dist: pre-commit (==1.17.0) ; extra == 'code_style'
Requires-Dist: doc8 (<0.9.0,>=0.8.0) ; extra == 'code_style'
Provides-Extra: docs
Requires-Dist: sphinx (>=1.6) ; extra == 'docs'
Requires-Dist: ipypublish (>=0.10.7) ; extra == 'docs'
Provides-Extra: testing
Requires-Dist: mock (==2.0.0) ; extra == 'testing'
Requires-Dist: pgtest (==1.2.0) ; extra == 'testing'
Requires-Dist: sqlalchemy-diff (==0.1.3) ; extra == 'testing'
Requires-Dist: pytest (==3.6.3) ; extra == 'testing'
Requires-Dist: wheel (>=0.31) ; extra == 'testing'
Requires-Dist: coverage ; extra == 'testing'
Requires-Dist: pytest-cov ; extra == 'testing'
Requires-Dist: pytest-timeout ; extra == 'testing'
Requires-Dist: pytest-regressions ; extra == 'testing'
Requires-Dist: pytest-notebook ; (python_version >= "3.5") and extra == 'testing'
